re_renamer/__init__.py
re_renamer/__main__.py
re_renamer/app.py
re_renamer/cli.py
re_renamer/logging.py
re_renamer/path_row.py
re_renamer/style.tcss
re_renamer/text_plus.py
re_renamer/screens/__init__.py
re_renamer/screens/disable_overwrite_protection_modal.py
re_renamer/widgets/__init__.py
re_renamer/widgets/buttons.py
re_renamer/widgets/inputs.py
re_renamer/widgets/log.py
re_renamer/widgets/options.py
re_renamer/widgets/table.py
re_renamer-0.1.1.dist-info/LICENSE
re_renamer-0.1.1.dist-info/METADATA
re_renamer-0.1.1.dist-info/WHEEL
re_renamer-0.1.1.dist-info/entry_points.txt
re_renamer-0.1.1.dist-info/top_level.txt
re_renamer-0.1.1.dist-info/RECORD
