Metadata-Version: 2.1
Name: re-renamer
Version: 0.1.1
Summary: [RE]name files and folders with [RE]gex.
Author-email: Josh Duncan <joshbduncan@gmail.com>
License: MIT License
Keywords: rename,regex,utility,tui
Classifier: Intended Audience :: End Users/Desktop
Classifier: License :: OSI Approved :: MIT License
Classifier: Natural Language :: English
Classifier: Operating System :: OS Independent
Classifier: Programming Language :: Python
Classifier: Programming Language :: Python :: 3.11
Classifier: Programming Language :: Python :: 3.12
Classifier: Typing :: Typed
Requires-Python: >=3.11
License-File: LICENSE
Requires-Dist: rich ==13.6.0
Requires-Dist: textual ==0.38.1
Provides-Extra: dev
Requires-Dist: black >=23.9.1 ; extra == 'dev'
Requires-Dist: flake8 >=6.1.0 ; extra == 'dev'
Requires-Dist: isort >=5.12.0 ; extra == 'dev'
Requires-Dist: mypy >=1.5.1 ; extra == 'dev'
Requires-Dist: pytest >=7.4.0 ; extra == 'dev'
Requires-Dist: pytest-cov >=4.1.0 ; extra == 'dev'
Requires-Dist: pytest-asyncio >=0.21.0 ; extra == 'dev'
Requires-Dist: ruff >=0.0.292 ; extra == 'dev'
Requires-Dist: textual-dev >=1.2.1 ; extra == 'dev'
